cloudside/__init__.py
cloudside/asos.py
cloudside/cli.py
cloudside/exporters.py
cloudside/hydra.py
cloudside/ncdc.py
cloudside/storms.py
cloudside/validate.py
cloudside/viz.py
cloudside/tests/__init__.py
cloudside/tests/test_asos.py
cloudside/tests/test_cli.py
cloudside/tests/test_exporters.py
cloudside/tests/test_hydra.py
cloudside/tests/test_ncdc.py
cloudside/tests/test_storms.py
cloudside/tests/test_validate.py
cloudside/tests/test_viz.py
cloudside/tests/baseline_images/__init__.py
cloudside/tests/baseline_images/viz_tests/__init__.py
cloudside/tests/baseline_images/viz_tests/test_hyetograph.png
cloudside/tests/baseline_images/viz_tests/test_psychromograph.png
cloudside/tests/baseline_images/viz_tests/test_rain_clock.png
cloudside/tests/baseline_images/viz_tests/test_rose.png
cloudside/tests/baseline_images/viz_tests/test_rose_short.png
cloudside/tests/baseline_images/viz_tests/test_temperature.png
cloudside/tests/baseline_images/viz_tests/test_windrose.png
cloudside/tests/baseline_images/viz_tests/test_windrose_short.png
cloudside/tests/data/__init__.py
cloudside/tests/data/data_for_tests.csv
cloudside/tests/data/data_for_viz_tests.csv
cloudside/tests/data/known_CSV_from_NCDC.csv
cloudside/tests/data/known_fivemin_swmm5.dat
cloudside/tests/data/known_hourly_NCDC.dat
cloudside/tests/data/known_hourly_swmm5.dat
cloudside/tests/data/nsd_cccc.txt
cloudside/tests/data/sample_asos.csv
cloudside/tests/data/sample_asos.dat
cloudside/tests/data/sample_hydra.txt
cloudside/tests/data/sample_ncdc_data.csv
cloudside/tests/data/sample_wunder.dat
cloudside/tests/data/teststorm_firstobs.csv
cloudside/tests/data/teststorm_simple.csv
cloudside/tests/data/teststorm_singular.csv
cloudside-0.3.0.dist-info/LICENSE
cloudside-0.3.0.dist-info/METADATA
cloudside-0.3.0.dist-info/WHEEL
cloudside-0.3.0.dist-info/entry_points.txt
cloudside-0.3.0.dist-info/top_level.txt
cloudside-0.3.0.dist-info/RECORD
