Metadata-Version: 2.1
Name: cloudside
Version: 0.3.0
Summary: cloudside - download, assess, and visualize weather data
Home-page: https://github.com/Geosyntec/cloudside
Author: Paul Hobson
Author-email: pmhobson@gmail.com
License: BSD 3-Clause
Platform: Python 3.8 and later.
Classifier: Development Status :: 3 - Alpha
Classifier: Environment :: Console
Classifier: Intended Audience :: Science/Research
Classifier: License :: OSI Approved :: BSD License
Classifier: Operating System :: OS Independent
Classifier: Programming Language :: Python :: 3.8
Classifier: Topic :: Scientific/Engineering :: Atmospheric Science
Classifier: Topic :: Scientific/Engineering :: Visualization
Requires-Python: >=3.8
License-File: LICENSE
Requires-Dist: click
Requires-Dist: requests
Requires-Dist: numpy
Requires-Dist: matplotlib
Requires-Dist: pandas
Requires-Dist: tqdm
Requires-Dist: metar>=1.5
Provides-Extra: dev
Requires-Dist: black; extra == "dev"
Requires-Dist: codecov; extra == "dev"
Requires-Dist: coverage; extra == "dev"
Requires-Dist: flake8; extra == "dev"
Requires-Dist: pytest; extra == "dev"
Requires-Dist: pytest-flake8; extra == "dev"
Requires-Dist: pytest-mpl; extra == "dev"
Requires-Dist: pytest-cov; extra == "dev"
